lab4/Register/shift_register.vhd
library ieee;
use ieee.std_logic_1164.all;

entity srg_4 is 
port(clk, reset, SI: in std_logic;
     Q: out std_logic_vector(3 downto 0);
     SO: out std_logic);
end srg_4;

architecture behavioral of srg_4 is
    signal shift: std_logic_vector(3 downto 0);
    begin
        process(reset, clk)
    begin 
        if (reset='1') then shift<= "0000";
        elsif (clk' event and (clk='1')) then shift <= shift(2 downto 0) & SI;
        end if;
        end process;
        Q<=shift;
        SO<=shift(3);
end behavioral;

lab4/Register/tb_srg_4.vhd
library ieee;
use ieee.std_logic_1164.all;

entity tb_srg_4 is
end tb_srg_4;

architecture behavior of tb_srg_4 is
    -- Signal declarations for inputs and outputs
    signal clk    : std_logic := '0';
    signal reset  : std_logic := '0';
    signal SI     : std_logic := '0';
    signal Q      : std_logic_vector(3 downto 0);
    signal SO     : std_logic;
    
    -- Clock period definition
    constant clk_period : time := 10 ns;

begin

    -- Instantiate the Unit Under Test (UUT)
    UUT: entity work.srg_4
        port map (
            clk => clk,
            reset => reset,
            SI => SI,
            Q => Q,
            SO => SO
        );

    -- Clock generation process
    clk_process : process
    begin
        while now < 100 ns loop  -- Run the clock for 100 ns
            clk <= '0';
            wait for clk_period ;
            clk <= '1';
            wait for clk_period;
        end loop;
        wait;  -- Stop the clock after 100 ns
    end process;

    -- Stimulus process to provide inputs
    stim_process : process
    begin
        -- Apply reset
        reset <= '1';
        wait for 20 ns;
        reset <= '0';  -- Deassert reset

        -- Apply test stimulus to SI
        SI <= '1';  -- Load first '1' into the shift register
        wait for 10 ns;

        SI <= '0';  -- Shift in '0'
        wait for 10 ns;

        SI <= '1';  -- Shift in '1'
        wait for 10 ns;

        SI <= '1';  -- Shift in '1'
        wait for 10 ns;

        SI <= '0';  -- Shift in '0'
        wait for 10 ns;

        -- Continue running for a bit to observe SO behavior
        wait for 30 ns;

        wait;
    end process;

end behavior;

lab4/Register/shif_wave1.vcd
$date
  Thu Oct  3 14:45:12 2024
$end
$version
  GHDL v0
$end
$timescale
  1 fs
$end
$scope module standard $end
$upscope $end
$scope module std_logic_1164 $end
$upscope $end
$scope module tb_srg_4 $end
$var reg 1 ! clk $end
$var reg 1 " reset $end
$var reg 1 # si $end
$var reg 4 $ q[3:0] $end
$var reg 1 % so $end
$scope module uut $end
$var reg 1 & clk $end
$var reg 1 ' reset $end
$var reg 1 ( si $end
$var reg 4 ) q[3:0] $end
$var reg 1 * so $end
$var reg 4 + shift[3:0] $end
$upscope $end
$upscope $end
$enddefinitions $end
#0
0!
1"
0#
b0000 $
0%
0&
1'
0(
b0000 )
0*
b0000 +
#5000000
1!
1&
#10000000
0!
0&
#15000000
1!
1&
#20000000
0!
0"
1#
0&
0'
1(
#25000000
1!
b0001 $
1&
b0001 )
b0001 +
#30000000
0!
0#
0&
0(
#35000000
1!
b0010 $
1&
b0010 )
b0010 +
#40000000
0!
1#
0&
1(
#45000000
1!
b0101 $
1&
b0101 )
b0101 +
#50000000
0!
0&
#55000000
1!
b1011 $
1%
1&
b1011 )
1*
b1011 +
#60000000
0!
0#
0&
0(
#65000000
1!
b0110 $
0%
1&
b0110 )
0*
b0110 +
#70000000
0!
0&
#75000000
1!
b1100 $
1%
1&
b1100 )
1*
b1100 +
#80000000
0!
0&
#85000000
1!
b1000 $
1&
b1000 )
b1000 +
#90000000
0!
0&
#95000000
1!
b0000 $
0%
1&
b0000 )
0*
b0000 +
