lab4/Register/4bit_register.vhd
library ieee;
use ieee.std_logic_1164.all;

entity rg_4 is 
port(clk, clear: in std_logic;
     D: in std_logic_vector(3 downto 0);
     Q: out std_logic_vector(3 downto 0));
end rg_4;

architecture behavioral of rg_4 is 
signal Q_i: std_logic_vector(3 downto 0);
begin 
    process(clk, clear)
    begin
        if clear='0' then Q_i <= (others => '0');
        elsif (clk'event and clk='1') then Q_i <= D;
        end if;
        Q <= Q_i;
    end process;
end behavioral;

lab4/Register/testbench.vhd
library ieee;
use ieee.std_logic_1164.all;

entity tb_rg_4 is
end tb_rg_4;

architecture behavior of tb_rg_4 is

    -- Signal declarations
    signal clk   : std_logic := '0';
    signal clear : std_logic := '1';
    signal D     : std_logic_vector(3 downto 0);
    signal Q     : std_logic_vector(3 downto 0);

    constant clk_period : time := 10 ns;

begin

    -- Instantiate the Unit Under Test (UUT)
    UUT: entity work.rg_4
        port map (
            clk => clk,
            clear => clear,
            D => D,
            Q => Q
        );
    
    clk_process : process
    begin
        while now < 100 ns loop 
            clk <= '0';
            wait for clk_period ;
            clk <= '1';
            wait for clk_period;
        end loop;
        wait;  
    end process;
    stim_process : process
    begin
        clear <= '0';
        wait for 20 ns;

        clear <= '1';
        D <= "1010"; 
        wait for 10 ns;

        D <= "1100"; 
        wait for 10 ns;

        clear <= '0';  
        wait for 10 ns;

        clear <= '1';
        D <= "0111"; 
        wait for 10 ns;

        wait;
    end process;

end behavior;

lab4/Register/wave_form.vcd
$date
  Thu Oct  3 14:38:13 2024
$end
$version
  GHDL v0
$end
$timescale
  1 fs
$end
$scope module standard $end
$upscope $end
$scope module std_logic_1164 $end
$upscope $end
$scope module tb_rg_4 $end
$var reg 1 ! clk $end
$var reg 1 " clear $end
$var reg 4 # d[3:0] $end
$var reg 4 $ q[3:0] $end
$scope module uut $end
$var reg 1 % clk $end
$var reg 1 & clear $end
$var reg 4 ' d[3:0] $end
$var reg 4 ( q[3:0] $end
$var reg 4 ) q_i[3:0] $end
$upscope $end
$upscope $end
$enddefinitions $end
#0
0!
0"
bUUUU #
bUUUU $
0%
0&
bUUUU '
bUUUU (
b0000 )
#5000000
1!
b0000 $
1%
b0000 (
#10000000
0!
0%
#15000000
1!
1%
#20000000
0!
1"
b1010 #
0%
1&
b1010 '
#25000000
1!
1%
b1010 )
#30000000
0!
b1100 #
b1010 $
0%
b1100 '
b1010 (
#35000000
1!
1%
b1100 )
#40000000
0!
0"
b1100 $
0%
0&
b1100 (
b0000 )
#45000000
1!
b0000 $
1%
b0000 (
#50000000
0!
1"
b0111 #
0%
1&
b0111 '
#55000000
1!
1%
b0111 )
#60000000
0!
b0111 $
0%
b0111 (
