lab2/divide/by3/behavioral.vhd
library IEEE;
use IEEE.STD_LOGIC_1164.ALL;

entity prime3 is
   port ( N: in  STD_LOGIC_VECTOR(3 DOWNTO 0);
          F: out STD_LOGIC);
end prime3;

architecture prime_arch_beh of prime3 is
   -- Function to convert STD_LOGIC_VECTOR to INTEGER
   function CONV_INTEGER (X: STD_LOGIC_VECTOR) return INTEGER is
      variable RESULT: INTEGER := 0;
   begin
      for i in X'range loop
         RESULT := RESULT * 2;
         if X(i) = '1' then
            RESULT := RESULT + 1;
         end if;
      end loop;
      return RESULT;
   end function;

begin
   -- Behavioral description using a process block
   process(N)
      variable NI: INTEGER;
   begin
      NI := CONV_INTEGER(N);  -- Convert binary input to integer
      if NI = 3 or NI = 6 or NI = 9 or NI = 12 or NI = 15 then
         F <= '1';
      else
         F <= '0';
      end if;
   end process;
end prime_arch_beh;

lab2/divide/by3/dataflow.vhd
library IEEE;
use IEEE.STD_LOGIC_1164.ALL;

entity prime2 is
   port ( N: in  STD_LOGIC_VECTOR(3 DOWNTO 0);
          F: out STD_LOGIC);
end prime2;

architecture prime2_arch_datafl of prime2 is
begin
   -- Dataflow description using Boolean equations\
with N select	
  F <= '1' when "0011",
 	'1' when "0110", 
	'1' when "1001" | "1100" | "1111",
	 '0' when others;
end prime2_arch_datafl;

lab2/prime_struct/or4.vhd
library ieee;
use ieee.std_logic_1164.all;

entity OR4 is 
port (
    in1: in std_logic;
    in2: in std_logic;
    in3: in std_logic;
    in4: in std_logic;
    out1: out std_logic);
end OR4;

architecture and_arch of OR4 is 
begin
    out1 <= in1 or in2 or in3 or in4;
end and_arch;

lab2/prime_struct/and3.vhd
library ieee;
use ieee.std_logic_1164.all;

entity AND3 is 
port (
    in1: in std_logic;
    in2: in std_logic;
    in3: in std_logic;
    out1: out std_logic);
end AND3;

architecture and_arch of AND3 is 
begin
    out1 <= in1 and in2 and in3;
end and_arch;

lab2/divide/by3/and2.vhd
library ieee;
use ieee.std_logic_1164.all;

entity AND2 is 
port (
    in1: in std_logic;
    in2: in std_logic;
    out1: out std_logic);
end AND2;

architecture and_arch of AND2 is 
begin
    out1 <= in1 and in2;
end and_arch;

lab2/prime_struct/inv.vhd
library ieee;
use ieee.std_logic_1164.all;

entity INV is 
port (
    in1: in std_logic;
    out1: out std_logic);
end INV;

architecture and_arch of INV is 
begin
    out1 <= not in1;
end and_arch;

lab2/prime_struct/prime1.vhd
library IEEE;
use IEEE.STD_LOGIC_1164.ALL;

entity prime1 is
   port ( N: in  STD_LOGIC_VECTOR(3 DOWNTO 0);
          F: out STD_LOGIC);
end prime1;

architecture prime_arch_struct of prime1 is
   signal N3_L, N2_L, N1_L: STD_LOGIC;
   signal N3L_N0, N3L_N2L_N1, N2L_N1_N0, N2_N1L_N0: STD_LOGIC;

   component INV
      port(In1: in STD_LOGIC; Out1: out STD_LOGIC);
   end component;

   component AND2
      port(In1, In2: in STD_LOGIC; Out1: out STD_LOGIC);
   end component;

   component AND3
      port(In1, In2, In3: in STD_LOGIC; Out1: out STD_LOGIC);
   end component;

   component OR4
      port(In1, In2, In3, In4: in STD_LOGIC; Out1: out STD_LOGIC);
   end component;

begin
   -- Instantiate Inverters
   U1: INV port map (N(3), N3_L);
   U2: INV port map (N(2), N2_L);
   U3: INV port map (N(1), N1_L);

   -- Instantiate AND gates
   U4: AND2 port map (N3_L, N(0), N3L_N0);
   U5: AND3 port map (N3_L, N2_L, N(1), N3L_N2L_N1);
   U6: AND3 port map (N2_L, N(1), N(0), N2L_N1_N0);
   U7: AND3 port map (N(2), N1_L, N(0), N2_N1L_N0);

   -- Instantiate OR gate
   U8: OR4 port map (N3L_N0, N3L_N2L_N1, N2L_N1_N0, N2_N1L_N0, F);
end prime_arch_struct;

lab2/divide/by3/testbench.vhd
library IEEE;
use IEEE.STD_LOGIC_1164.ALL;

entity prime_tb is
end prime_tb;

architecture prime_tb_arch of prime_tb is
   component prime1
      port ( N: in  STD_LOGIC_VECTOR(3 DOWNTO 0);
             F: out STD_LOGIC);
   end component;
   component prime2
      port ( N: in  STD_LOGIC_VECTOR(3 DOWNTO 0);
             F: out STD_LOGIC);
   end component;
   component prime3
      port ( N: in  STD_LOGIC_VECTOR(3 DOWNTO 0);
             F: out STD_LOGIC);
   end component;

   signal NT : STD_LOGIC_VECTOR(3 DOWNTO 0);
   signal FT1, FT2, FT3: STD_LOGIC;
begin
   -- Instantiate the prime number detector
   UU1: prime1 port map (NT, FT1);
   UU2: prime2 port map (NT, FT2);
   UU3: prime3 port map (NT, FT3);

   -- Stimulus process
   process
   begin
      NT <= "0000"; wait for 10 ns;
      NT <= "0001"; wait for 10 ns;
      NT <= "0010"; wait for 10 ns;
      NT <= "0011"; wait for 10 ns;
      NT <= "0100"; wait for 10 ns;
      NT <= "0101"; wait for 10 ns;
      NT <= "0110"; wait for 10 ns;
      NT <= "0111"; wait for 10 ns;
      NT <= "1000"; wait for 10 ns;
      NT <= "1001"; wait for 10 ns;
      NT <= "1010"; wait for 10 ns;
      NT <= "1011"; wait for 10 ns;
      NT <= "1100"; wait for 10 ns;
      NT <= "1101"; wait for 10 ns;
      NT <= "1110"; wait for 10 ns;
      NT <= "1111"; wait for 10 ns;
      wait;
   end process;
end prime_tb_arch;

lab2/divide/by3/wave2.vcd
$date
  Thu Sep 12 14:31:32 2024
$end
$version
  GHDL v0
$end
$timescale
  1 fs
$end
$scope module standard $end
$upscope $end
$scope module std_logic_1164 $end
$upscope $end
$scope module prime_tb $end
$var reg 4 ! nt[3:0] $end
$var reg 1 " ft1 $end
$var reg 1 # ft2 $end
$var reg 1 $ ft3 $end
$scope module uu1 $end
$var reg 4 % n[3:0] $end
$var reg 1 & f $end
$var reg 1 ' n3_l $end
$var reg 1 ( n2_l $end
$var reg 1 ) n1_l $end
$var reg 1 * n3l_n0 $end
$var reg 1 + n3l_n2l_n1 $end
$var reg 1 , n2l_n1_n0 $end
$var reg 1 - n2_n1l_n0 $end
$scope module u1 $end
$var reg 1 . in1 $end
$var reg 1 / out1 $end
$upscope $end
$scope module u2 $end
$var reg 1 0 in1 $end
$var reg 1 1 out1 $end
$upscope $end
$scope module u3 $end
$var reg 1 2 in1 $end
$var reg 1 3 out1 $end
$upscope $end
$scope module u4 $end
$var reg 1 4 in1 $end
$var reg 1 5 in2 $end
$var reg 1 6 out1 $end
$upscope $end
$scope module u5 $end
$var reg 1 7 in1 $end
$var reg 1 8 in2 $end
$var reg 1 9 in3 $end
$var reg 1 : out1 $end
$upscope $end
$scope module u6 $end
$var reg 1 ; in1 $end
$var reg 1 < in2 $end
$var reg 1 = in3 $end
$var reg 1 > out1 $end
$upscope $end
$scope module u7 $end
$var reg 1 ? in1 $end
$var reg 1 @ in2 $end
$var reg 1 A in3 $end
$var reg 1 B out1 $end
$upscope $end
$scope module u8 $end
$var reg 1 C in1 $end
$var reg 1 D in2 $end
$var reg 1 E in3 $end
$var reg 1 F in4 $end
$var reg 1 G out1 $end
$upscope $end
$upscope $end
$scope module uu2 $end
$var reg 4 H n[3:0] $end
$var reg 1 I f $end
$upscope $end
$scope module uu3 $end
$var reg 4 J n[3:0] $end
$var reg 1 K f $end
$upscope $end
$upscope $end
$enddefinitions $end
#0
b0000 !
0"
0#
0$
b0000 %
0&
1'
1(
1)
0*
0+
0,
0-
0.
1/
00
11
02
13
14
05
06
17
18
09
0:
1;
0<
0=
0>
0?
1@
0A
0B
0C
0D
0E
0F
0G
b0000 H
0I
b0000 J
0K
#10000000
b0001 !
1"
b0001 %
1&
1*
15
16
1=
1A
1C
1G
b0001 H
b0001 J
#20000000
b0010 !
b0010 %
0)
0*
1+
12
03
05
06
19
1:
1<
0=
0@
0A
0C
1D
b0010 H
b0010 J
#30000000
b0011 !
1#
1$
b0011 %
1*
1,
15
16
1=
1>
1A
1C
1E
b0011 H
1I
b0011 J
1K
#40000000
b0100 !
0"
0#
0$
b0100 %
0&
0(
1)
0*
0+
0,
10
01
02
13
05
06
08
09
0:
0;
0<
0=
0>
1?
1@
0A
0C
0D
0E
0G
b0100 H
0I
b0100 J
0K
#50000000
b0101 !
1"
b0101 %
1&
1*
1-
15
16
1=
1A
1B
1C
1F
1G
b0101 H
b0101 J
#60000000
b0110 !
0"
1#
1$
b0110 %
0&
0)
0*
0-
12
03
05
06
19
1<
0=
0@
0A
0B
0C
0F
0G
b0110 H
1I
b0110 J
1K
#70000000
b0111 !
1"
0#
0$
b0111 %
1&
1*
15
16
1=
1A
1C
1G
b0111 H
0I
b0111 J
0K
#80000000
b1000 !
0"
b1000 %
0&
0'
1(
1)
0*
1.
0/
00
11
02
13
04
05
06
07
18
09
1;
0<
0=
0?
1@
0A
0C
0G
b1000 H
b1000 J
#90000000
b1001 !
1#
1$
b1001 %
15
1=
1A
b1001 H
1I
b1001 J
1K
#100000000
b1010 !
0#
0$
b1010 %
0)
12
03
05
19
1<
0=
0@
0A
b1010 H
0I
b1010 J
0K
#110000000
b1011 !
1"
b1011 %
1&
1,
15
1=
1>
1A
1E
1G
b1011 H
b1011 J
#120000000
b1100 !
0"
1#
1$
b1100 %
0&
0(
1)
0,
10
01
02
13
05
08
09
0;
0<
0=
0>
1?
1@
0A
0E
0G
b1100 H
1I
b1100 J
1K
#130000000
b1101 !
1"
0#
0$
b1101 %
1&
1-
15
1=
1A
1B
1F
1G
b1101 H
0I
b1101 J
0K
#140000000
b1110 !
0"
b1110 %
0&
0)
0-
12
03
05
19
1<
0=
0@
0A
0B
0F
0G
b1110 H
b1110 J
#150000000
b1111 !
1#
1$
b1111 %
15
1=
1A
b1111 H
1I
b1111 J
1K
