lab2/prime_struct/or4.vhd
library ieee;
use ieee.std_logic_1164.all;

entity OR4 is 
port (
    in1: in std_logic;
    in2: in std_logic;
    in3: in std_logic;
    in4: in std_logic;
    out1: out std_logic);
end OR4;

architecture and_arch of OR4 is 
begin
    out1 <= in1 or in2 or in3 or in4;
end and_arch;

lab2/prime_struct/and3.vhd
library ieee;
use ieee.std_logic_1164.all;

entity AND3 is 
port (
    in1: in std_logic;
    in2: in std_logic;
    in3: in std_logic;
    out1: out std_logic);
end AND3;

architecture and_arch of AND3 is 
begin
    out1 <= in1 and in2 and in3;
end and_arch;

lab2/divide/by3/and2.vhd
library ieee;
use ieee.std_logic_1164.all;

entity AND2 is 
port (
    in1: in std_logic;
    in2: in std_logic;
    out1: out std_logic);
end AND2;

architecture and_arch of AND2 is 
begin
    out1 <= in1 and in2;
end and_arch;

lab2/prime_struct/inv.vhd
library ieee;
use ieee.std_logic_1164.all;

entity INV is 
port (
    in1: in std_logic;
    out1: out std_logic);
end INV;

architecture and_arch of INV is 
begin
    out1 <= not in1;
end and_arch;

lab2/prime_struct/prime1.vhd
library IEEE;
use IEEE.STD_LOGIC_1164.ALL;

entity prime1 is
   port ( N: in  STD_LOGIC_VECTOR(3 DOWNTO 0);
          F: out STD_LOGIC);
end prime1;

architecture prime_arch_struct of prime1 is
   signal N3_L, N2_L, N1_L: STD_LOGIC;
   signal N3L_N0, N3L_N2L_N1, N2L_N1_N0, N2_N1L_N0: STD_LOGIC;

   component INV
      port(In1: in STD_LOGIC; Out1: out STD_LOGIC);
   end component;

   component AND2
      port(In1, In2: in STD_LOGIC; Out1: out STD_LOGIC);
   end component;

   component AND3
      port(In1, In2, In3: in STD_LOGIC; Out1: out STD_LOGIC);
   end component;

   component OR4
      port(In1, In2, In3, In4: in STD_LOGIC; Out1: out STD_LOGIC);
   end component;

begin
   -- Instantiate Inverters
   U1: INV port map (N(3), N3_L);
   U2: INV port map (N(2), N2_L);
   U3: INV port map (N(1), N1_L);

   -- Instantiate AND gates
   U4: AND2 port map (N3_L, N(0), N3L_N0);
   U5: AND3 port map (N3_L, N2_L, N(1), N3L_N2L_N1);
   U6: AND3 port map (N2_L, N(1), N(0), N2L_N1_N0);
   U7: AND3 port map (N(2), N1_L, N(0), N2_N1L_N0);

   -- Instantiate OR gate
   U8: OR4 port map (N3L_N0, N3L_N2L_N1, N2L_N1_N0, N2_N1L_N0, F);
end prime_arch_struct;

lab2/prime_struct/strcut_testbench.vhd
library IEEE;
use IEEE.STD_LOGIC_1164.ALL;

entity prime_tb is
end prime_tb;

architecture prime_tb_arch of prime_tb is
   component prime1
      port ( N: in  STD_LOGIC_VECTOR(3 DOWNTO 0);
             F: out STD_LOGIC);
   end component;
   component prime2
      port ( N: in  STD_LOGIC_VECTOR(3 DOWNTO 0);
             F: out STD_LOGIC);
   end component;
   component prime3
      port ( N: in  STD_LOGIC_VECTOR(3 DOWNTO 0);
             F: out STD_LOGIC);
   end component;
   component prime4
      port ( N: in  STD_LOGIC_VECTOR(3 DOWNTO 0);
             F: out STD_LOGIC);
   end component;

   signal NT : STD_LOGIC_VECTOR(3 DOWNTO 0);
   signal FT1, FT2, FT3, FT4: STD_LOGIC;
begin
   -- Instantiate the prime number detector
   UU1: prime1 port map (NT, FT1);
   UU2: prime1 port map (NT, FT2);
   UU3: prime1 port map (NT, FT3);
   UU4: prime1 port map (NT, FT4);

   -- Stimulus process
   process
   begin
      NT <= "0000"; wait for 10 ns;
      NT <= "0001"; wait for 10 ns;
      NT <= "0010"; wait for 10 ns;
      NT <= "0011"; wait for 10 ns;
      NT <= "0100"; wait for 10 ns;
      NT <= "0101"; wait for 10 ns;
      NT <= "0110"; wait for 10 ns;
      NT <= "0111"; wait for 10 ns;
      NT <= "1000"; wait for 10 ns;
      NT <= "1001"; wait for 10 ns;
      NT <= "1010"; wait for 10 ns;
      NT <= "1011"; wait for 10 ns;
      NT <= "1100"; wait for 10 ns;
      NT <= "1101"; wait for 10 ns;
      NT <= "1110"; wait for 10 ns;
      NT <= "1111"; wait for 10 ns;
      wait;
   end process;
end prime_tb_arch;

lab2/divide/by3/wave.vcd
$date
  Thu Sep 12 14:21:44 2024
$end
$version
  GHDL v0
$end
$timescale
  1 fs
$end
$scope module standard $end
$upscope $end
$scope module std_logic_1164 $end
$upscope $end
$scope module prime_tb $end
$var reg 4 ! nt[3:0] $end
$var reg 1 " ft1 $end
$scope module uu1 $end
$var reg 4 # n[3:0] $end
$var reg 1 $ f $end
$upscope $end
$upscope $end
$enddefinitions $end
#0
b0000 !
0"
b0000 #
0$
#10000000
b0001 !
b0001 #
#20000000
b0010 !
b0010 #
#30000000
b0011 !
1"
b0011 #
1$
#40000000
b0100 !
0"
b0100 #
0$
#50000000
b0101 !
b0101 #
#60000000
b0110 !
1"
b0110 #
1$
#70000000
b0111 !
0"
b0111 #
0$
#80000000
b1000 !
b1000 #
#90000000
b1001 !
1"
b1001 #
1$
#100000000
b1010 !
0"
b1010 #
0$
#110000000
b1011 !
b1011 #
#120000000
b1100 !
1"
b1100 #
1$
#130000000
b1101 !
0"
b1101 #
0$
#140000000
b1110 !
b1110 #
#150000000
b1111 !
1"
b1111 #
1$
