lab2/divide/by3/behavioral.vhd
library IEEE;
use IEEE.STD_LOGIC_1164.ALL;

entity prime3 is
   port ( N: in  STD_LOGIC_VECTOR(3 DOWNTO 0);
          F: out STD_LOGIC);
end prime3;

architecture prime_arch_beh of prime3 is
   function CONV_INTEGER (X: STD_LOGIC_VECTOR) return INTEGER is
      variable RESULT: INTEGER := 0;
   begin
      for i in X'range loop
         RESULT := RESULT * 2;
         if X(i) = '1' then
            RESULT := RESULT + 1;
         end if;
      end loop;
      return RESULT;
   end function;
   begin
      process(N)
         variable NI: INTEGER;
      begin
         NI := CONV_INTEGER(N);
         if NI = 3 or NI = 6 or NI = 9 or NI = 12 or NI = 15 then
            F <= '1';
         else
            F <= '0';
         end if;
      end process;
end prime_arch_beh;

lab2/divide/by3/dataflow.vhd
library IEEE;
use IEEE.STD_LOGIC_1164.ALL;

entity prime2 is
   port ( N: in  STD_LOGIC_VECTOR(3 DOWNTO 0);
          F: out STD_LOGIC);
end prime2;

architecture prime2_arch_datafl of prime2 is
begin
with N select	
  F <= '1' when "0011",
 	'1' when "0110", 
	'1' when "1001" | "1100" | "1111",
	 '0' when others;
end prime2_arch_datafl;

lab2/divide/by3/or5.vhd
library ieee;
use ieee.std_logic_1164.all;

entity or5 is 
port(in1: in std_logic;
     in2: in std_logic;
     in3: in std_logic;
     in4: in std_logic;
     in5: in std_logic;
     out1: out std_logic);
end or5;

architecture or5_arch of or5 is
begin
    out1 <= in1 or in2 or in3 or in4 or in5;
end or5_arch;

lab2/divide/by3/and4.vhd
library ieee;
use ieee.std_logic_1164.all;

entity and4 is
port (in1: in std_logic;
     in2: in std_logic;
     in3: in std_logic;
     in4: in std_logic;
     out1: out std_logic
);
end and4;

architecture and4_arch of and4 is
begin 
    out1 <= in1 and in2 and in3 and in4;
end and4_arch;

lab2/prime_struct/inv.vhd
library ieee;
use ieee.std_logic_1164.all;

entity INV is 
port (
    in1: in std_logic;
    out1: out std_logic);
end INV;

architecture and_arch of INV is 
begin
    out1 <= not in1;
end and_arch;

lab2/divide/by3/structural.vhd
library IEEE;
use IEEE.STD_LOGIC_1164.ALL;

entity divider is
    port ( N: in  STD_LOGIC_VECTOR(3 DOWNTO 0);
          F: out STD_LOGIC);
end divider;

architecture divider_arch of divider is
    signal notand_a, notand_b, notand_c, notand_d:std_logic;
    signal out_a, out_b, out_c, out_d, out_e:std_logic;
    component INV
      port(in1: in STD_LOGIC; out1: out STD_LOGIC);
   end component;
   component and4
      port(in1, in2, in3, in4: in STD_LOGIC; out1: out STD_LOGIC);
   end component;
   component or5
      port(in1, in2, in3, in4, in5: in STD_LOGIC; out1: out STD_LOGIC);
   end component;
begin
    U1: INV port map(N(0), notand_a);
    U2: INV port map(N(1), notand_b);
    U3: INV port map(N(2), notand_c);
    U4: INV port map(N(3), notand_d);
    
    F1: and4 port map(notand_a, notand_b, N(2), N(3), out_a);
    F2: and4 port map(notand_a, N(1), N(2), notand_d, out_b);
    F3: and4 port map(N(0), notand_b, notand_c, N(3), out_c);
    F4: and4 port map(N(0), N(1), notand_c, notand_d, out_d);
    F5: and4 port map(N(0), N(1), N(2), N(3), out_e);

    E1: or5 port map(out_a, out_b, out_c, out_d, out_e, F);
end divider_arch;

lab2/divide/by3/testbench.vhd
library IEEE;
use IEEE.STD_LOGIC_1164.ALL;

entity prime_tb is
end prime_tb;

architecture prime_tb_arch of prime_tb is
   component divider
      port ( N: in  STD_LOGIC_VECTOR(3 DOWNTO 0);
             F: out STD_LOGIC);
   end component;
   component prime2
      port ( N: in  STD_LOGIC_VECTOR(3 DOWNTO 0);
             F: out STD_LOGIC);
   end component;
   component prime3
      port ( N: in  STD_LOGIC_VECTOR(3 DOWNTO 0);
             F: out STD_LOGIC);
   end component;

   signal NT : STD_LOGIC_VECTOR(3 DOWNTO 0);
   signal FT1, FT2, FT3: STD_LOGIC;
begin
   UU1: divider port map (NT, FT1);
   UU2: prime2 port map (NT, FT2);
   UU3: prime3 port map (NT, FT3);
process
   begin
      NT <= "0000"; wait for 10 ns;
      NT <= "0001"; wait for 10 ns;
      NT <= "0010"; wait for 10 ns;
      NT <= "0011"; wait for 10 ns;
      NT <= "0100"; wait for 10 ns;
      NT <= "0101"; wait for 10 ns;
      NT <= "0110"; wait for 10 ns;
      NT <= "0111"; wait for 10 ns;
      NT <= "1000"; wait for 10 ns;
      NT <= "1001"; wait for 10 ns;
      NT <= "1010"; wait for 10 ns;
      NT <= "1011"; wait for 10 ns;
      NT <= "1100"; wait for 10 ns;
      NT <= "1101"; wait for 10 ns;
      NT <= "1110"; wait for 10 ns;
      NT <= "1111"; wait for 10 ns;
      wait;
   end process;
end prime_tb_arch;

lab2/divide/by3/wave1.vcd
$date
  Tue Oct  1 16:22:55 2024
$end
$version
  GHDL v0
$end
$timescale
  1 fs
$end
$scope module standard $end
$upscope $end
$scope module std_logic_1164 $end
$upscope $end
$scope module prime_tb $end
$var reg 4 ! nt[3:0] $end
$var reg 1 " ft1 $end
$var reg 1 # ft2 $end
$var reg 1 $ ft3 $end
$scope module uu1 $end
$var reg 4 % n[3:0] $end
$var reg 1 & f $end
$var reg 1 ' notand_a $end
$var reg 1 ( notand_b $end
$var reg 1 ) notand_c $end
$var reg 1 * notand_d $end
$var reg 1 + out_a $end
$var reg 1 , out_b $end
$var reg 1 - out_c $end
$var reg 1 . out_d $end
$var reg 1 / out_e $end
$scope module u1 $end
$var reg 1 0 in1 $end
$var reg 1 1 out1 $end
$upscope $end
$scope module u2 $end
$var reg 1 2 in1 $end
$var reg 1 3 out1 $end
$upscope $end
$scope module u3 $end
$var reg 1 4 in1 $end
$var reg 1 5 out1 $end
$upscope $end
$scope module u4 $end
$var reg 1 6 in1 $end
$var reg 1 7 out1 $end
$upscope $end
$scope module f1 $end
$var reg 1 8 in1 $end
$var reg 1 9 in2 $end
$var reg 1 : in3 $end
$var reg 1 ; in4 $end
$var reg 1 < out1 $end
$upscope $end
$scope module f2 $end
$var reg 1 = in1 $end
$var reg 1 > in2 $end
$var reg 1 ? in3 $end
$var reg 1 @ in4 $end
$var reg 1 A out1 $end
$upscope $end
$scope module f3 $end
$var reg 1 B in1 $end
$var reg 1 C in2 $end
$var reg 1 D in3 $end
$var reg 1 E in4 $end
$var reg 1 F out1 $end
$upscope $end
$scope module f4 $end
$var reg 1 G in1 $end
$var reg 1 H in2 $end
$var reg 1 I in3 $end
$var reg 1 J in4 $end
$var reg 1 K out1 $end
$upscope $end
$scope module f5 $end
$var reg 1 L in1 $end
$var reg 1 M in2 $end
$var reg 1 N in3 $end
$var reg 1 O in4 $end
$var reg 1 P out1 $end
$upscope $end
$scope module e1 $end
$var reg 1 Q in1 $end
$var reg 1 R in2 $end
$var reg 1 S in3 $end
$var reg 1 T in4 $end
$var reg 1 U in5 $end
$var reg 1 V out1 $end
$upscope $end
$upscope $end
$scope module uu2 $end
$var reg 4 W n[3:0] $end
$var reg 1 X f $end
$upscope $end
$scope module uu3 $end
$var reg 4 Y n[3:0] $end
$var reg 1 Z f $end
$upscope $end
$upscope $end
$enddefinitions $end
#0
b0000 !
0"
0#
0$
b0000 %
0&
1'
1(
1)
1*
0+
0,
0-
0.
0/
00
11
02
13
04
15
06
17
18
19
0:
0;
0<
1=
0>
0?
1@
0A
0B
1C
1D
0E
0F
0G
0H
1I
1J
0K
0L
0M
0N
0O
0P
0Q
0R
0S
0T
0U
0V
b0000 W
0X
b0000 Y
0Z
#10000000
b0001 !
b0001 %
0'
10
01
08
0=
1B
1G
1L
b0001 W
b0001 Y
#20000000
b0010 !
b0010 %
1'
0(
00
11
12
03
18
09
1=
1>
0B
0C
0G
1H
0L
1M
b0010 W
b0010 Y
#30000000
b0011 !
1"
1#
1$
b0011 %
1&
0'
1.
10
01
08
0=
1B
1G
1K
1L
1T
1V
b0011 W
1X
b0011 Y
1Z
#40000000
b0100 !
0"
0#
0$
b0100 %
0&
1'
1(
0)
0.
00
11
02
13
14
05
18
19
1:
1=
0>
1?
0B
1C
0D
0G
0H
0I
0K
0L
0M
1N
0T
0V
b0100 W
0X
b0100 Y
0Z
#50000000
b0101 !
b0101 %
0'
10
01
08
0=
1B
1G
1L
b0101 W
b0101 Y
#60000000
b0110 !
1"
1#
1$
b0110 %
1&
1'
0(
1,
00
11
12
03
18
09
1=
1>
1A
0B
0C
0G
1H
0L
1M
1R
1V
b0110 W
1X
b0110 Y
1Z
#70000000
b0111 !
0"
0#
0$
b0111 %
0&
0'
0,
10
01
08
0=
0A
1B
1G
1L
0R
0V
b0111 W
0X
b0111 Y
0Z
#80000000
b1000 !
b1000 %
1'
1(
1)
0*
00
11
02
13
04
15
16
07
18
19
0:
1;
1=
0>
0?
0@
0B
1C
1D
1E
0G
0H
1I
0J
0L
0M
0N
1O
b1000 W
b1000 Y
#90000000
b1001 !
1"
1#
1$
b1001 %
1&
0'
1-
10
01
08
0=
1B
1F
1G
1L
1S
1V
b1001 W
1X
b1001 Y
1Z
#100000000
b1010 !
0"
0#
0$
b1010 %
0&
1'
0(
0-
00
11
12
03
18
09
1=
1>
0B
0C
0F
0G
1H
0L
1M
0S
0V
b1010 W
0X
b1010 Y
0Z
#110000000
b1011 !
b1011 %
0'
10
01
08
0=
1B
1G
1L
b1011 W
b1011 Y
#120000000
b1100 !
1"
1#
1$
b1100 %
1&
1'
1(
0)
1+
00
11
02
13
14
05
18
19
1:
1<
1=
0>
1?
0B
1C
0D
0G
0H
0I
0L
0M
1N
1Q
1V
b1100 W
1X
b1100 Y
1Z
#130000000
b1101 !
0"
0#
0$
b1101 %
0&
0'
0+
10
01
08
0<
0=
1B
1G
1L
0Q
0V
b1101 W
0X
b1101 Y
0Z
#140000000
b1110 !
b1110 %
1'
0(
00
11
12
03
18
09
1=
1>
0B
0C
0G
1H
0L
1M
b1110 W
b1110 Y
#150000000
b1111 !
1"
1#
1$
b1111 %
1&
0'
1/
10
01
08
0=
1B
1G
1L
1P
1U
1V
b1111 W
1X
b1111 Y
1Z
