lab5/Synchronous_counter/jkff.vhd
library ieee;
use ieee.std_logic_1164.all;

entity jkff is
    port(clk, rst, j, k:in std_logic;
        q, qn          :out std_logic);
end jkff;

architecture rtl of jkff is 
    signal ff:std_logic:= '0';
begin 
    process(clk, rst)
        variable jk: std_logic_vector(1 downto 0);
    begin
        if(rst = '0') then 
            ff<= '0';
        elsif (clk'event and clk='1') then
            jk:= j & k;
            case jk is 
                when "01" => ff <='0';
                when "10" => ff <='1';
                when "11" => ff <=not ff;
                when others => ff <=ff;
            end case;
        end if;
    end process;
    q <= ff after 1 ns;
    qn <= not ff after 1 ns;
end rtl;

lab5/Synchronous_counter/as_cnt.vhd
library ieee;
use ieee.std_logic_1164.all;

entity as_cnt is 
    port(rst, a_clk: in std_logic;
         cntr      : out std_logic_vector(3 downto 0));
end as_cnt;

architecture rtl of as_cnt is 
    component jkff port(clk, rst, j, k:in std_logic;
                        q, qn          :out std_logic);
    end component;
    signal ffq: std_logic_vector(4 downto 0) := "00000";
    signal ffqn: std_logic_vector(4 downto 0):= "11111";
    signal vdd: std_logic:= '1';
begin 
    vdd <= '1'; ffqn(0) <= a_clk;
    jk0: for j in 1 to 4 generate 
        uu0: jkff port map (clk => ffqn(j-1), rst => rst,   
                j => vdd, k => vdd, q => ffq(j), qn => ffqn(j));
    end generate;
    cntr <= ffq(4 downto 1);
end rtl;

lab5/Synchronous_counter/as_test_bench.vhd
library ieee;
use ieee.std_logic_1164.all;

entity tb_as_cnt is
end tb_as_cnt;

architecture behavior of tb_as_cnt is

    -- Component Declaration for the Unit Under Test (UUT)
    component as_cnt
        port(
            rst   : in std_logic;
            a_clk : in std_logic;
            cntr  : out std_logic_vector(3 downto 0)
        );
    end component;

    -- Signals to connect to the UUT
    signal rst   : std_logic := '0';
    signal a_clk : std_logic := '0';
    signal cntr  : std_logic_vector(3 downto 0);

    -- Clock period definition
    constant clk_period : time :=20 ns;

begin

    -- Instantiate the Unit Under Test (UUT)
    uut: as_cnt
        port map (
            rst   => rst,
            a_clk => a_clk,
            cntr  => cntr
        );

    -- Clock process definitions
    clk_process :process
    begin
        while now < 440 ns loop  -- Set simulation time limit to 200 nanoseconds
            a_clk <= '0';
            wait for clk_period/2;
            a_clk <= '1';
            wait for clk_period/2;
        end loop;
        wait;  -- Stop the simulation
    end process;

    -- Stimulus process
    stim_proc: process
    begin
        -- Initialize Inputs
        rst <= '1';
        wait for 100 ns;
        
        rst <= '0';  -- Release reset
        wait for 10 ns;
        
        rst <= '1';  -- Assert reset again
        wait for 320 ns;
        
        rst <= '0';  -- Release reset
        wait for 10 ns;
        
        -- Add more stimulus as needed
        wait;  -- Wait indefinitely
    end process;

end behavior;

lab5/Synchronous_counter/as_test_last.vcd
$date
  Thu Oct 31 14:22:01 2024
$end
$version
  GHDL v0
$end
$timescale
  1 fs
$end
$scope module standard $end
$upscope $end
$scope module std_logic_1164 $end
$upscope $end
$scope module tb_as_cnt $end
$var reg 1 ! rst $end
$var reg 1 " a_clk $end
$var reg 4 # cntr[3:0] $end
$scope module uut $end
$var reg 1 $ rst $end
$var reg 1 % a_clk $end
$var reg 4 & cntr[3:0] $end
$var reg 5 ' ffq[4:0] $end
$var reg 5 ( ffqn[4:0] $end
$var reg 1 ) vdd $end
$scope module jk0(1) $end
$scope module uu0 $end
$var reg 1 * clk $end
$var reg 1 + rst $end
$var reg 1 , j $end
$var reg 1 - k $end
$var reg 1 . q $end
$var reg 1 / qn $end
$var reg 1 0 ff $end
$upscope $end
$upscope $end
$scope module jk0(2) $end
$scope module uu0 $end
$var reg 1 1 clk $end
$var reg 1 2 rst $end
$var reg 1 3 j $end
$var reg 1 4 k $end
$var reg 1 5 q $end
$var reg 1 6 qn $end
$var reg 1 7 ff $end
$upscope $end
$upscope $end
$scope module jk0(3) $end
$scope module uu0 $end
$var reg 1 8 clk $end
$var reg 1 9 rst $end
$var reg 1 : j $end
$var reg 1 ; k $end
$var reg 1 < q $end
$var reg 1 = qn $end
$var reg 1 > ff $end
$upscope $end
$upscope $end
$scope module jk0(4) $end
$scope module uu0 $end
$var reg 1 ? clk $end
$var reg 1 @ rst $end
$var reg 1 A j $end
$var reg 1 B k $end
$var reg 1 C q $end
$var reg 1 D qn $end
$var reg 1 E ff $end
$upscope $end
$upscope $end
$upscope $end
$upscope $end
$enddefinitions $end
#0
1!
0"
bUUUU #
1$
0%
bUUUU &
bUUUU0 '
bUUUU0 (
1)
0*
1+
1,
1-
U.
U/
00
U1
12
13
14
U5
U6
07
U8
19
1:
1;
U<
U=
0>
U?
1@
1A
1B
UC
UD
0E
#1000000
b0000 #
b0000 &
b00000 '
b11110 (
0.
1/
11
05
16
17
18
0<
1=
1>
1?
0C
1D
1E
#2000000
b1110 #
b1110 &
b11100 '
b00010 (
15
06
08
1<
0=
0?
1C
0D
#10000000
1"
1%
b00011 (
1*
10
#11000000
b1111 #
b1111 &
b11110 '
b00001 (
1.
0/
01
#20000000
0"
0%
b00000 (
0*
#30000000
1"
1%
b00001 (
1*
00
#31000000
b1110 #
b1110 &
b11100 '
b00011 (
0.
1/
11
07
#32000000
b1100 #
b1100 &
b11000 '
b00111 (
05
16
18
0>
#33000000
b1000 #
b1000 &
b10000 '
b01111 (
0<
1=
1?
0E
#34000000
b0000 #
b0000 &
b00000 '
b11111 (
0C
1D
#40000000
0"
0%
b11110 (
0*
#50000000
1"
1%
b11111 (
1*
10
#51000000
b0001 #
b0001 &
b00010 '
b11101 (
1.
0/
01
#60000000
0"
0%
b11100 (
0*
#70000000
1"
1%
b11101 (
1*
00
#71000000
b0000 #
b0000 &
b00000 '
b11111 (
0.
1/
11
17
#72000000
b0010 #
b0010 &
b00100 '
b11011 (
15
06
08
#80000000
0"
0%
b11010 (
0*
#90000000
1"
1%
b11011 (
1*
10
#91000000
b0011 #
b0011 &
b00110 '
b11001 (
1.
0/
01
#100000000
0!
0"
0$
0%
b11000 (
0*
0+
00
02
07
09
0@
#101000000
b0000 #
b0000 &
b00000 '
b11110 (
0.
1/
11
05
16
18
#110000000
1!
1"
1$
1%
b11111 (
1*
1+
10
12
19
1@
#111000000
b0001 #
b0001 &
b00010 '
b11101 (
1.
0/
01
#120000000
0"
0%
b11100 (
0*
#130000000
1"
1%
b11101 (
1*
00
#131000000
b0000 #
b0000 &
b00000 '
b11111 (
0.
1/
11
17
#132000000
b0010 #
b0010 &
b00100 '
b11011 (
15
06
08
#140000000
0"
0%
b11010 (
0*
#150000000
1"
1%
b11011 (
1*
10
#151000000
b0011 #
b0011 &
b00110 '
b11001 (
1.
0/
01
#160000000
0"
0%
b11000 (
0*
#170000000
1"
1%
b11001 (
1*
00
#171000000
b0010 #
b0010 &
b00100 '
b11011 (
0.
1/
11
07
#172000000
b0000 #
b0000 &
b00000 '
b11111 (
05
16
18
1>
#173000000
b0100 #
b0100 &
b01000 '
b10111 (
1<
0=
0?
#180000000
0"
0%
b10110 (
0*
#190000000
1"
1%
b10111 (
1*
10
#191000000
b0101 #
b0101 &
b01010 '
b10101 (
1.
0/
01
#200000000
0"
0%
b10100 (
0*
#210000000
1"
1%
b10101 (
1*
00
#211000000
b0100 #
b0100 &
b01000 '
b10111 (
0.
1/
11
17
#212000000
b0110 #
b0110 &
b01100 '
b10011 (
15
06
08
#220000000
0"
0%
b10010 (
0*
#230000000
1"
1%
b10011 (
1*
10
#231000000
b0111 #
b0111 &
b01110 '
b10001 (
1.
0/
01
#240000000
0"
0%
b10000 (
0*
#250000000
1"
1%
b10001 (
1*
00
#251000000
b0110 #
b0110 &
b01100 '
b10011 (
0.
1/
11
07
#252000000
b0100 #
b0100 &
b01000 '
b10111 (
05
16
18
0>
#253000000
b0000 #
b0000 &
b00000 '
b11111 (
0<
1=
1?
1E
#254000000
b1000 #
b1000 &
b10000 '
b01111 (
1C
0D
#260000000
0"
0%
b01110 (
0*
#270000000
1"
1%
b01111 (
1*
10
#271000000
b1001 #
b1001 &
b10010 '
b01101 (
1.
0/
01
#280000000
0"
0%
b01100 (
0*
#290000000
1"
1%
b01101 (
1*
00
#291000000
b1000 #
b1000 &
b10000 '
b01111 (
0.
1/
11
17
#292000000
b1010 #
b1010 &
b10100 '
b01011 (
15
06
08
#300000000
0"
0%
b01010 (
0*
#310000000
1"
1%
b01011 (
1*
10
#311000000
b1011 #
b1011 &
b10110 '
b01001 (
1.
0/
01
#320000000
0"
0%
b01000 (
0*
#330000000
1"
1%
b01001 (
1*
00
#331000000
b1010 #
b1010 &
b10100 '
b01011 (
0.
1/
11
07
#332000000
b1000 #
b1000 &
b10000 '
b01111 (
05
16
18
1>
#333000000
b1100 #
b1100 &
b11000 '
b00111 (
1<
0=
0?
#340000000
0"
0%
b00110 (
0*
#350000000
1"
1%
b00111 (
1*
10
#351000000
b1101 #
b1101 &
b11010 '
b00101 (
1.
0/
01
#360000000
0"
0%
b00100 (
0*
#370000000
1"
1%
b00101 (
1*
00
#371000000
b1100 #
b1100 &
b11000 '
b00111 (
0.
1/
11
17
#372000000
b1110 #
b1110 &
b11100 '
b00011 (
15
06
08
#380000000
0"
0%
b00010 (
0*
#390000000
1"
1%
b00011 (
1*
10
#391000000
b1111 #
b1111 &
b11110 '
b00001 (
1.
0/
01
#400000000
0"
0%
b00000 (
0*
#410000000
1"
1%
b00001 (
1*
00
#411000000
b1110 #
b1110 &
b11100 '
b00011 (
0.
1/
11
07
#412000000
b1100 #
b1100 &
b11000 '
b00111 (
05
16
18
0>
#413000000
b1000 #
b1000 &
b10000 '
b01111 (
0<
1=
1?
0E
#414000000
b0000 #
b0000 &
b00000 '
b11111 (
0C
1D
#420000000
0"
0%
b11110 (
0*
#430000000
0!
1"
0$
1%
b11111 (
1*
0+
02
09
0@
