lab5/Synchronous_counter/s_cnt_.vhd
library ieee;
use ieee.std_logic_1164.all;
use ieee.numeric_std.all;

entity s_cnt is 
    port(
        clk  : in std_logic;
        rst  : in std_logic;
        en   : in std_logic;
        cntr : out std_logic_vector(7 downto 0)
    );
end s_cnt;

architecture rtl of s_cnt is 
    signal ff: unsigned(7 downto 0) := (others => '0');
begin 
    process(clk, rst)
    begin 
        if rst = '0' then      
            ff <= (others => '0');
        elsif rising_edge(clk) then   
            if en = '1' then 
                ff <= ff + 1;
            end if;
        end if;
    end process;
    cntr <= std_logic_vector(ff);
end rtl;

lab5/Synchronous_counter/s_test_testbech.vhd
library ieee;
use ieee.std_logic_1164.all;
use ieee.numeric_std.all;

entity tb_s_cnt is
end tb_s_cnt;

architecture behavior of tb_s_cnt is

    component s_cnt
        port(
            clk  : in std_logic;
            rst  : in std_logic;
            en   : in std_logic;
            cntr : out std_logic_vector(7 downto 0)
        );
    end component;

    signal clk  : std_logic := '0';
    signal rst  : std_logic := '0';
    signal en   : std_logic := '0';
    signal cntr : std_logic_vector(7 downto 0);
    constant clk_period : time := 10 ns;

begin
    uut: s_cnt port map (
        clk  => clk,
        rst  => rst,
        en   => en,
        cntr => cntr
    );

    clk_process :process
    begin
        while now < 480  ns loop
            clk <= '0';
            wait for clk_period/2;
            clk <= '1';
            wait for clk_period/2;
        end loop;
        wait;
    end process;

    stim_proc: process
    begin
        rst <= '0';
        wait for 20 ns;
        
        rst <= '1'; 
        wait for 10 ns;
        
        en <= '1';
        wait for 200 ns;
        
        en <= '0';
        wait for 50 ns;
        
        en <= '1';
        wait for 200 ns;

        wait;
    end process;

end behavior;

lab5/Synchronous_counter/s_bech.vcd
$date
  Thu Oct 31 14:54:09 2024
$end
$version
  GHDL v0
$end
$timescale
  1 fs
$end
$scope module standard $end
$upscope $end
$scope module std_logic_1164 $end
$upscope $end
$scope module numeric_std $end
$upscope $end
$scope module tb_s_cnt $end
$var reg 1 ! clk $end
$var reg 1 " rst $end
$var reg 1 # en $end
$var reg 8 $ cntr[7:0] $end
$scope module uut $end
$var reg 1 % clk $end
$var reg 1 & rst $end
$var reg 1 ' en $end
$var reg 8 ( cntr[7:0] $end
$var reg 8 ) ff[7:0] $end
$upscope $end
$upscope $end
$enddefinitions $end
#0
0!
0"
0#
b00000000 $
0%
0&
0'
b00000000 (
b00000000 )
#5000000
1!
1%
#10000000
0!
0%
#15000000
1!
1%
#20000000
0!
1"
0%
1&
#25000000
1!
1%
#30000000
0!
1#
0%
1'
#35000000
1!
b00000001 $
1%
b00000001 (
b00000001 )
#40000000
0!
0%
#45000000
1!
b00000010 $
1%
b00000010 (
b00000010 )
#50000000
0!
0%
#55000000
1!
b00000011 $
1%
b00000011 (
b00000011 )
#60000000
0!
0%
#65000000
1!
b00000100 $
1%
b00000100 (
b00000100 )
#70000000
0!
0%
#75000000
1!
b00000101 $
1%
b00000101 (
b00000101 )
#80000000
0!
0%
#85000000
1!
b00000110 $
1%
b00000110 (
b00000110 )
#90000000
0!
0%
#95000000
1!
b00000111 $
1%
b00000111 (
b00000111 )
#100000000
0!
0%
#105000000
1!
b00001000 $
1%
b00001000 (
b00001000 )
#110000000
0!
0%
#115000000
1!
b00001001 $
1%
b00001001 (
b00001001 )
#120000000
0!
0%
#125000000
1!
b00001010 $
1%
b00001010 (
b00001010 )
#130000000
0!
0%
#135000000
1!
b00001011 $
1%
b00001011 (
b00001011 )
#140000000
0!
0%
#145000000
1!
b00001100 $
1%
b00001100 (
b00001100 )
#150000000
0!
0%
#155000000
1!
b00001101 $
1%
b00001101 (
b00001101 )
#160000000
0!
0%
#165000000
1!
b00001110 $
1%
b00001110 (
b00001110 )
#170000000
0!
0%
#175000000
1!
b00001111 $
1%
b00001111 (
b00001111 )
#180000000
0!
0%
#185000000
1!
b00010000 $
1%
b00010000 (
b00010000 )
#190000000
0!
0%
#195000000
1!
b00010001 $
1%
b00010001 (
b00010001 )
#200000000
0!
0%
#205000000
1!
b00010010 $
1%
b00010010 (
b00010010 )
#210000000
0!
0%
#215000000
1!
b00010011 $
1%
b00010011 (
b00010011 )
#220000000
0!
0%
#225000000
1!
b00010100 $
1%
b00010100 (
b00010100 )
#230000000
0!
0#
0%
0'
#235000000
1!
1%
#240000000
0!
0%
#245000000
1!
1%
#250000000
0!
0%
#255000000
1!
1%
#260000000
0!
0%
#265000000
1!
1%
#270000000
0!
0%
#275000000
1!
1%
#280000000
0!
1#
0%
1'
#285000000
1!
b00010101 $
1%
b00010101 (
b00010101 )
#290000000
0!
0%
#295000000
1!
b00010110 $
1%
b00010110 (
b00010110 )
#300000000
0!
0%
#305000000
1!
b00010111 $
1%
b00010111 (
b00010111 )
#310000000
0!
0%
#315000000
1!
b00011000 $
1%
b00011000 (
b00011000 )
#320000000
0!
0%
#325000000
1!
b00011001 $
1%
b00011001 (
b00011001 )
#330000000
0!
0%
#335000000
1!
b00011010 $
1%
b00011010 (
b00011010 )
#340000000
0!
0%
#345000000
1!
b00011011 $
1%
b00011011 (
b00011011 )
#350000000
0!
0%
#355000000
1!
b00011100 $
1%
b00011100 (
b00011100 )
#360000000
0!
0%
#365000000
1!
b00011101 $
1%
b00011101 (
b00011101 )
#370000000
0!
0%
#375000000
1!
b00011110 $
1%
b00011110 (
b00011110 )
#380000000
0!
0%
#385000000
1!
b00011111 $
1%
b00011111 (
b00011111 )
#390000000
0!
0%
#395000000
1!
b00100000 $
1%
b00100000 (
b00100000 )
#400000000
0!
0%
#405000000
1!
b00100001 $
1%
b00100001 (
b00100001 )
#410000000
0!
0%
#415000000
1!
b00100010 $
1%
b00100010 (
b00100010 )
#420000000
0!
0%
#425000000
1!
b00100011 $
1%
b00100011 (
b00100011 )
#430000000
0!
0%
#435000000
1!
b00100100 $
1%
b00100100 (
b00100100 )
#440000000
0!
0%
#445000000
1!
b00100101 $
1%
b00100101 (
b00100101 )
#450000000
0!
0%
#455000000
1!
b00100110 $
1%
b00100110 (
b00100110 )
#460000000
0!
0%
#465000000
1!
b00100111 $
1%
b00100111 (
b00100111 )
#470000000
0!
0%
#475000000
1!
b00101000 $
1%
b00101000 (
b00101000 )
