lab1/adder.vhd
library ieee;
use ieee.std_logic_1164.all;

entity full_adder is port (
    A, B, Ci : in std_logic;
    S, Co: out std_logic);
end full_adder;

architecture behavior of full_adder is 
begin
    s <= A xor B xor Ci;
    co <= (A and B) or (Ci and (A xor B));
end behavior;

lab1/addertest.vhd
library ieee;
use ieee.std_logic_1164.all;

entity addertest is end addertest;
architecture behavior of addertest is
     component full_adder port(
               A, B, Ci: in std_logic;
               S, Co: out std_logic);
     end component;
     signal AT, BT, Cin:  std_logic;
     signal  Sum, Cout: std_logic;
begin
     U1: full_adder port map(A=>At, B=>Bt, Ci=>Cin, S=>Sum, Co=>Cout);
     process
     begin
          AT <= '1';BT <= '1';Cin <= '1';
          wait for 100 ns; 
          AT <= '1';BT <= '1';Cin <= '0';
          wait for 100 ns; 
          AT <= '1';BT <= '0';Cin <= '1';
          wait for 100 ns;
          AT <= '1';BT <= '0';Cin <= '0';
          wait for 100 ns;
          AT <= '0';BT <= '1';Cin <= '1';
          wait for 100 ns;   
          AT <= '0';BT <= '1';Cin <= '0';
          wait for 100 ns;
          AT <= '0';BT <= '0';Cin <= '1';
          wait for 100 ns;
          AT <= '0';BT <= '0';Cin <= '0';
          wait ;
    end process;
end behavior;

lab1/ad.vcd
$date
  Thu Sep 26 09:08:58 2024
$end
$version
  GHDL v0
$end
$timescale
  1 fs
$end
$scope module standard $end
$upscope $end
$scope module std_logic_1164 $end
$upscope $end
$scope module addertest $end
$var reg 1 ! at $end
$var reg 1 " bt $end
$var reg 1 # cin $end
$var reg 1 $ sum $end
$var reg 1 % cout $end
$scope module u1 $end
$var reg 1 & a $end
$var reg 1 ' b $end
$var reg 1 ( ci $end
$var reg 1 ) s $end
$var reg 1 * co $end
$upscope $end
$upscope $end
$enddefinitions $end
#0
1!
1"
1#
1$
1%
1&
1'
1(
1)
1*
#100000000
0#
0$
0(
0)
#200000000
0"
1#
0'
1(
#300000000
0#
1$
0%
0(
1)
0*
#400000000
0!
1"
1#
0$
1%
0&
1'
1(
0)
1*
#500000000
0#
1$
0%
0(
1)
0*
#600000000
0"
1#
0'
1(
#700000000
0#
0$
0(
0)
