lab1/adder.vhd
-- Comments in VHDL start with --
 -- Ying Li
 -- A full adder
 -- import useful packages
library ieee;
use ieee.std_logic_1164.all; -- provide enhanced signal types
-- filename must be the same as entity name
-- entity defines the inputs and outputs of the circuit 
entity adder is
-- A, B, Ci are inputs
-- S and Co are the outputs
port (
    A, B, Ci : in std_logic; -- std_logic represent one bit signal 
    S, Co: out std_logic -- that can take on the value 0 or 1 
    );
end adder;
 -- architecture define the circuit
architecture behavior of adder is 
begin
    -- statements in the architecture enclosed by begin and end are executed concurrently -- compute the sum
    s <= A xor B xor ci; -- <= assign the result of A xor B xor ci to s
    -- compute the carry
    co <= (A and B) or ((a xor b) and ci); -- VHDL is case-insensitive 
end behavior;

lab1/addertest.vhd
-- Ying Li
 -- A testbench for the full adder
 library ieee;
 use ieee.std_logic_1164.all;
 -- A testbench has no ports
entity addertest is end addertest;
architecture behavior of addertest is
-- Declaration of the component that will be instantiated 
component adder
        port(
             A, B, Ci: in std_logic;
             S, Co: out std_logic
        );
     end component;
     -- the adder signals
     signal I0, I1, I2, O0, O1 : std_logic;
begin
-- component instantiation
-- connect the inputs and outputs of the entity to the local signals 
    adder1 : adder port map (A=>I0, B=>I1, Ci=>I2, Co=>O0, S=>O1);
    I0 <= '0', '1' after 4 ns; -- send signals to port a, the signal is 0 in the first 4 ns and 1 afterward
            I1 <= '0', '1' after 2 ns, '0' after 4 ns, '1' after 6 ns;
            I2 <= '0', '1' after 1 ns, '0' after 2 ns, '1' after 3 ns, '0' after 4 ns, '1' after 5
     ns, '0' after 6 ns, '1' after 7 ns, '0' after 8 ns;
end behavior;

lab1/adder.vcd
$date
  Wed Sep 11 16:33:22 2024
$end
$version
  GHDL v0
$end
$timescale
  1 fs
$end
$scope module standard $end
$upscope $end
$scope module std_logic_1164 $end
$upscope $end
$scope module addertest $end
$var reg 1 ! i0 $end
$var reg 1 " i1 $end
$var reg 1 # i2 $end
$var reg 1 $ o0 $end
$var reg 1 % o1 $end
$scope module adder1 $end
$var reg 1 & a $end
$var reg 1 ' b $end
$var reg 1 ( ci $end
$var reg 1 ) s $end
$var reg 1 * co $end
$upscope $end
$upscope $end
$enddefinitions $end
#0
0!
0"
0#
0$
0%
0&
0'
0(
0)
0*
#1000000
1#
1%
1(
1)
#2000000
1"
0#
1'
0(
#3000000
1#
1$
0%
1(
0)
1*
#4000000
1!
0"
0#
0$
1%
1&
0'
0(
1)
0*
#5000000
1#
1$
0%
1(
0)
1*
#6000000
1"
0#
1'
0(
#7000000
1#
1%
1(
1)
#8000000
0#
0%
0(
0)
