lab1/multiplexer.vhd
library IEEE;
use IEEE.std_logic_1164.all;

entity mux2to1 is
    port (
        A, B, S: in std_logic;
        Z: out std_logic
    );
end mux2to1;

architecture mux_arch of mux2to1 is
begin
    Z <= A when S = '0' else B;
end mux_arch;

lab1/multitest.vhd
library IEEE;
use IEEE.std_logic_1164.all;

entity testbench is
end testbench;

architecture tb_arch of testbench is
    component mux2to1
        port (
            A, B, S: in std_logic;
            Z: out std_logic
        );
    end component;
    signal AT, BT, ST, ZT: std_logic;
begin
    U1: mux2to1 port map (A => AT, B => BT, S => ST, Z => ZT);
    process
    begin
        AT <= '0'; BT <= '0'; ST <= '0';
        wait for 100 ns;
        AT <= '1'; BT <= '0'; ST <= '0';
        wait for 100 ns;
        AT <= '1'; BT <= '1'; ST <= '0';
        wait for 100 ns;
        AT <= '0'; BT <= '1'; ST <= '0';
        wait for 100 ns;
        AT <= '0'; BT <= '0'; ST <= '1';
        wait for 100 ns;
        AT <= '1'; BT <= '0'; ST <= '1';
        wait for 100 ns;
        AT <= '1'; BT <= '1'; ST <= '1';
        wait for 100 ns;
        AT <= '0'; BT <= '1'; ST <= '1';
        wait;
    end process;
end tb_arch;

lab1/wavemux.vcd
$date
  Tue Sep 24 14:21:50 2024
$end
$version
  GHDL v0
$end
$timescale
  1 fs
$end
$scope module standard $end
$upscope $end
$scope module std_logic_1164 $end
$upscope $end
$scope module testbench $end
$var reg 1 ! at $end
$var reg 1 " bt $end
$var reg 1 # st $end
$var reg 1 $ zt $end
$scope module u1 $end
$var reg 1 % a $end
$var reg 1 & b $end
$var reg 1 ' s $end
$var reg 1 ( z $end
$upscope $end
$upscope $end
$enddefinitions $end
#0
0!
0"
0#
0$
0%
0&
0'
0(
#100000000
1!
1$
1%
1(
#200000000
1"
1&
#300000000
0!
0$
0%
0(
#400000000
0"
1#
0&
1'
#500000000
1!
1%
#600000000
1"
1$
1&
1(
#700000000
0!
0%
