lab2/prime_struct/or4.vhd
library ieee;
use ieee.std_logic_1164.all;

entity OR4 is 
port (
    in1: in std_logic;
    in2: in std_logic;
    in3: in std_logic;
    in4: in std_logic;
    out1: out std_logic);
end OR4;

architecture and_arch of OR4 is 
begin
    out1 <= in1 or in2 or in3 or in4;
end and_arch;

lab2/prime_struct/and3.vhd
library ieee;
use ieee.std_logic_1164.all;

entity AND3 is 
port (
    in1: in std_logic;
    in2: in std_logic;
    in3: in std_logic;
    out1: out std_logic);
end AND3;

architecture and_arch of AND3 is 
begin
    out1 <= in1 and in2 and in3;
end and_arch;

lab2/divide/by3/and2.vhd
library ieee;
use ieee.std_logic_1164.all;

entity AND2 is 
port (
    in1: in std_logic;
    in2: in std_logic;
    out1: out std_logic);
end AND2;

architecture and_arch of AND2 is 
begin
    out1 <= in1 and in2;
end and_arch;

lab2/prime_struct/inv.vhd
library ieee;
use ieee.std_logic_1164.all;

entity INV is 
port (
    in1: in std_logic;
    out1: out std_logic);
end INV;

architecture and_arch of INV is 
begin
    out1 <= not in1;
end and_arch;

lab2/prime_struct/prime1.vhd
library IEEE;
use IEEE.STD_LOGIC_1164.ALL;

entity prime1 is
   port ( N: in  STD_LOGIC_VECTOR(3 DOWNTO 0);
          F: out STD_LOGIC);
end prime1;

architecture prime_arch_struct of prime1 is
   signal N3_L, N2_L, N1_L: STD_LOGIC;
   signal N3L_N0, N3L_N2L_N1, N2L_N1_N0, N2_N1L_N0: STD_LOGIC;

   component INV
      port(In1: in STD_LOGIC; Out1: out STD_LOGIC);
   end component;

   component AND2
      port(In1, In2: in STD_LOGIC; Out1: out STD_LOGIC);
   end component;

   component AND3
      port(In1, In2, In3: in STD_LOGIC; Out1: out STD_LOGIC);
   end component;

   component OR4
      port(In1, In2, In3, In4: in STD_LOGIC; Out1: out STD_LOGIC);
   end component;

begin
   -- Instantiate Inverters
   U1: INV port map (N(3), N3_L);
   U2: INV port map (N(2), N2_L);
   U3: INV port map (N(1), N1_L);

   -- Instantiate AND gates
   U4: AND2 port map (N3_L, N(0), N3L_N0);
   U5: AND3 port map (N3_L, N2_L, N(1), N3L_N2L_N1);
   U6: AND3 port map (N2_L, N(1), N(0), N2L_N1_N0);
   U7: AND3 port map (N(2), N1_L, N(0), N2_N1L_N0);

   -- Instantiate OR gate
   U8: OR4 port map (N3L_N0, N3L_N2L_N1, N2L_N1_N0, N2_N1L_N0, F);
end prime_arch_struct;

lab2/prime_struct/strcut_testbench.vhd
library IEEE;
use IEEE.STD_LOGIC_1164.ALL;

entity prime_tb is
end prime_tb;

architecture prime_tb_arch of prime_tb is
   component prime1
      port ( N: in  STD_LOGIC_VECTOR(3 DOWNTO 0);
             F: out STD_LOGIC);
   end component;
   component prime2
      port ( N: in  STD_LOGIC_VECTOR(3 DOWNTO 0);
             F: out STD_LOGIC);
   end component;
   component prime3
      port ( N: in  STD_LOGIC_VECTOR(3 DOWNTO 0);
             F: out STD_LOGIC);
   end component;
   component prime4
      port ( N: in  STD_LOGIC_VECTOR(3 DOWNTO 0);
             F: out STD_LOGIC);
   end component;

   signal NT : STD_LOGIC_VECTOR(3 DOWNTO 0);
   signal FT1, FT2, FT3, FT4: STD_LOGIC;
begin
   -- Instantiate the prime number detector
   UU1: prime1 port map (NT, FT1);
   UU2: prime1 port map (NT, FT2);
   UU3: prime1 port map (NT, FT3);
   UU4: prime1 port map (NT, FT4);

   -- Stimulus process
   process
   begin
      NT <= "0000"; wait for 10 ns;
      NT <= "0001"; wait for 10 ns;
      NT <= "0010"; wait for 10 ns;
      NT <= "0011"; wait for 10 ns;
      NT <= "0100"; wait for 10 ns;
      NT <= "0101"; wait for 10 ns;
      NT <= "0110"; wait for 10 ns;
      NT <= "0111"; wait for 10 ns;
      NT <= "1000"; wait for 10 ns;
      NT <= "1001"; wait for 10 ns;
      NT <= "1010"; wait for 10 ns;
      NT <= "1011"; wait for 10 ns;
      NT <= "1100"; wait for 10 ns;
      NT <= "1101"; wait for 10 ns;
      NT <= "1110"; wait for 10 ns;
      NT <= "1111"; wait for 10 ns;
      wait;
   end process;
end prime_tb_arch;

lab2/prime_struct/wave.vcd
$date
  Thu Sep 12 14:01:46 2024
$end
$version
  GHDL v0
$end
$timescale
  1 fs
$end
$scope module standard $end
$upscope $end
$scope module std_logic_1164 $end
$upscope $end
$scope module prime_tb $end
$var reg 4 ! nt[3:0] $end
$var reg 1 " ft1 $end
$var reg 1 # ft2 $end
$var reg 1 $ ft3 $end
$var reg 1 % ft4 $end
$scope module uu1 $end
$var reg 4 & n[3:0] $end
$var reg 1 ' f $end
$var reg 1 ( n3_l $end
$var reg 1 ) n2_l $end
$var reg 1 * n1_l $end
$var reg 1 + n3l_n0 $end
$var reg 1 , n3l_n2l_n1 $end
$var reg 1 - n2l_n1_n0 $end
$var reg 1 . n2_n1l_n0 $end
$scope module u1 $end
$var reg 1 / in1 $end
$var reg 1 0 out1 $end
$upscope $end
$scope module u2 $end
$var reg 1 1 in1 $end
$var reg 1 2 out1 $end
$upscope $end
$scope module u3 $end
$var reg 1 3 in1 $end
$var reg 1 4 out1 $end
$upscope $end
$scope module u4 $end
$var reg 1 5 in1 $end
$var reg 1 6 in2 $end
$var reg 1 7 out1 $end
$upscope $end
$scope module u5 $end
$var reg 1 8 in1 $end
$var reg 1 9 in2 $end
$var reg 1 : in3 $end
$var reg 1 ; out1 $end
$upscope $end
$scope module u6 $end
$var reg 1 < in1 $end
$var reg 1 = in2 $end
$var reg 1 > in3 $end
$var reg 1 ? out1 $end
$upscope $end
$scope module u7 $end
$var reg 1 @ in1 $end
$var reg 1 A in2 $end
$var reg 1 B in3 $end
$var reg 1 C out1 $end
$upscope $end
$scope module u8 $end
$var reg 1 D in1 $end
$var reg 1 E in2 $end
$var reg 1 F in3 $end
$var reg 1 G in4 $end
$var reg 1 H out1 $end
$upscope $end
$upscope $end
$scope module uu2 $end
$var reg 4 I n[3:0] $end
$var reg 1 J f $end
$var reg 1 K n3_l $end
$var reg 1 L n2_l $end
$var reg 1 M n1_l $end
$var reg 1 N n3l_n0 $end
$var reg 1 O n3l_n2l_n1 $end
$var reg 1 P n2l_n1_n0 $end
$var reg 1 Q n2_n1l_n0 $end
$scope module u1 $end
$var reg 1 R in1 $end
$var reg 1 S out1 $end
$upscope $end
$scope module u2 $end
$var reg 1 T in1 $end
$var reg 1 U out1 $end
$upscope $end
$scope module u3 $end
$var reg 1 V in1 $end
$var reg 1 W out1 $end
$upscope $end
$scope module u4 $end
$var reg 1 X in1 $end
$var reg 1 Y in2 $end
$var reg 1 Z out1 $end
$upscope $end
$scope module u5 $end
$var reg 1 [ in1 $end
$var reg 1 \ in2 $end
$var reg 1 ] in3 $end
$var reg 1 ^ out1 $end
$upscope $end
$scope module u6 $end
$var reg 1 _ in1 $end
$var reg 1 ` in2 $end
$var reg 1 a in3 $end
$var reg 1 b out1 $end
$upscope $end
$scope module u7 $end
$var reg 1 c in1 $end
$var reg 1 d in2 $end
$var reg 1 e in3 $end
$var reg 1 f out1 $end
$upscope $end
$scope module u8 $end
$var reg 1 g in1 $end
$var reg 1 h in2 $end
$var reg 1 i in3 $end
$var reg 1 j in4 $end
$var reg 1 k out1 $end
$upscope $end
$upscope $end
$scope module uu3 $end
$var reg 4 l n[3:0] $end
$var reg 1 m f $end
$var reg 1 n n3_l $end
$var reg 1 o n2_l $end
$var reg 1 p n1_l $end
$var reg 1 q n3l_n0 $end
$var reg 1 r n3l_n2l_n1 $end
$var reg 1 s n2l_n1_n0 $end
$var reg 1 t n2_n1l_n0 $end
$scope module u1 $end
$var reg 1 u in1 $end
$var reg 1 v out1 $end
$upscope $end
$scope module u2 $end
$var reg 1 w in1 $end
$var reg 1 x out1 $end
$upscope $end
$scope module u3 $end
$var reg 1 y in1 $end
$var reg 1 z out1 $end
$upscope $end
$scope module u4 $end
$var reg 1 { in1 $end
$var reg 1 | in2 $end
$var reg 1 } out1 $end
$upscope $end
$scope module u5 $end
$var reg 1 !" in1 $end
$var reg 1 "" in2 $end
$var reg 1 #" in3 $end
$var reg 1 $" out1 $end
$upscope $end
$scope module u6 $end
$var reg 1 %" in1 $end
$var reg 1 &" in2 $end
$var reg 1 '" in3 $end
$var reg 1 (" out1 $end
$upscope $end
$scope module u7 $end
$var reg 1 )" in1 $end
$var reg 1 *" in2 $end
$var reg 1 +" in3 $end
$var reg 1 ," out1 $end
$upscope $end
$scope module u8 $end
$var reg 1 -" in1 $end
$var reg 1 ." in2 $end
$var reg 1 /" in3 $end
$var reg 1 0" in4 $end
$var reg 1 1" out1 $end
$upscope $end
$upscope $end
$scope module uu4 $end
$var reg 4 2" n[3:0] $end
$var reg 1 3" f $end
$var reg 1 4" n3_l $end
$var reg 1 5" n2_l $end
$var reg 1 6" n1_l $end
$var reg 1 7" n3l_n0 $end
$var reg 1 8" n3l_n2l_n1 $end
$var reg 1 9" n2l_n1_n0 $end
$var reg 1 :" n2_n1l_n0 $end
$scope module u1 $end
$var reg 1 ;" in1 $end
$var reg 1 <" out1 $end
$upscope $end
$scope module u2 $end
$var reg 1 =" in1 $end
$var reg 1 >" out1 $end
$upscope $end
$scope module u3 $end
$var reg 1 ?" in1 $end
$var reg 1 @" out1 $end
$upscope $end
$scope module u4 $end
$var reg 1 A" in1 $end
$var reg 1 B" in2 $end
$var reg 1 C" out1 $end
$upscope $end
$scope module u5 $end
$var reg 1 D" in1 $end
$var reg 1 E" in2 $end
$var reg 1 F" in3 $end
$var reg 1 G" out1 $end
$upscope $end
$scope module u6 $end
$var reg 1 H" in1 $end
$var reg 1 I" in2 $end
$var reg 1 J" in3 $end
$var reg 1 K" out1 $end
$upscope $end
$scope module u7 $end
$var reg 1 L" in1 $end
$var reg 1 M" in2 $end
$var reg 1 N" in3 $end
$var reg 1 O" out1 $end
$upscope $end
$scope module u8 $end
$var reg 1 P" in1 $end
$var reg 1 Q" in2 $end
$var reg 1 R" in3 $end
$var reg 1 S" in4 $end
$var reg 1 T" out1 $end
$upscope $end
$upscope $end
$upscope $end
$enddefinitions $end
#0
b0000 !
0"
0#
0$
0%
b0000 &
0'
1(
1)
1*
0+
0,
0-
0.
0/
10
01
12
03
14
15
06
07
18
19
0:
0;
1<
0=
0>
0?
0@
1A
0B
0C
0D
0E
0F
0G
0H
b0000 I
0J
1K
1L
1M
0N
0O
0P
0Q
0R
1S
0T
1U
0V
1W
1X
0Y
0Z
1[
1\
0]
0^
1_
0`
0a
0b
0c
1d
0e
0f
0g
0h
0i
0j
0k
b0000 l
0m
1n
1o
1p
0q
0r
0s
0t
0u
1v
0w
1x
0y
1z
1{
0|
0}
1!"
1""
0#"
0$"
1%"
0&"
0'"
0("
0)"
1*"
0+"
0,"
0-"
0."
0/"
00"
01"
b0000 2"
03"
14"
15"
16"
07"
08"
09"
0:"
0;"
1<"
0="
1>"
0?"
1@"
1A"
0B"
0C"
1D"
1E"
0F"
0G"
1H"
0I"
0J"
0K"
0L"
1M"
0N"
0O"
0P"
0Q"
0R"
0S"
0T"
#10000000
b0001 !
1"
1#
1$
1%
b0001 &
1'
1+
16
17
1>
1B
1D
1H
b0001 I
1J
1N
1Y
1Z
1a
1e
1g
1k
b0001 l
1m
1q
1|
1}
1'"
1+"
1-"
11"
b0001 2"
13"
17"
1B"
1C"
1J"
1N"
1P"
1T"
#20000000
b0010 !
b0010 &
0*
0+
1,
13
04
06
07
1:
1;
1=
0>
0A
0B
0D
1E
b0010 I
0M
0N
1O
1V
0W
0Y
0Z
1]
1^
1`
0a
0d
0e
0g
1h
b0010 l
0p
0q
1r
1y
0z
0|
0}
1#"
1$"
1&"
0'"
0*"
0+"
0-"
1."
b0010 2"
06"
07"
18"
1?"
0@"
0B"
0C"
1F"
1G"
1I"
0J"
0M"
0N"
0P"
1Q"
#30000000
b0011 !
b0011 &
1+
1-
16
17
1>
1?
1B
1D
1F
b0011 I
1N
1P
1Y
1Z
1a
1b
1e
1g
1i
b0011 l
1q
1s
1|
1}
1'"
1("
1+"
1-"
1/"
b0011 2"
17"
19"
1B"
1C"
1J"
1K"
1N"
1P"
1R"
#40000000
b0100 !
0"
0#
0$
0%
b0100 &
0'
0)
1*
0+
0,
0-
11
02
03
14
06
07
09
0:
0;
0<
0=
0>
0?
1@
1A
0B
0D
0E
0F
0H
b0100 I
0J
0L
1M
0N
0O
0P
1T
0U
0V
1W
0Y
0Z
0\
0]
0^
0_
0`
0a
0b
1c
1d
0e
0g
0h
0i
0k
b0100 l
0m
0o
1p
0q
0r
0s
1w
0x
0y
1z
0|
0}
0""
0#"
0$"
0%"
0&"
0'"
0("
1)"
1*"
0+"
0-"
0."
0/"
01"
b0100 2"
03"
05"
16"
07"
08"
09"
1="
0>"
0?"
1@"
0B"
0C"
0E"
0F"
0G"
0H"
0I"
0J"
0K"
1L"
1M"
0N"
0P"
0Q"
0R"
0T"
#50000000
b0101 !
1"
1#
1$
1%
b0101 &
1'
1+
1.
16
17
1>
1B
1C
1D
1G
1H
b0101 I
1J
1N
1Q
1Y
1Z
1a
1e
1f
1g
1j
1k
b0101 l
1m
1q
1t
1|
1}
1'"
1+"
1,"
1-"
10"
11"
b0101 2"
13"
17"
1:"
1B"
1C"
1J"
1N"
1O"
1P"
1S"
1T"
#60000000
b0110 !
0"
0#
0$
0%
b0110 &
0'
0*
0+
0.
13
04
06
07
1:
1=
0>
0A
0B
0C
0D
0G
0H
b0110 I
0J
0M
0N
0Q
1V
0W
0Y
0Z
1]
1`
0a
0d
0e
0f
0g
0j
0k
b0110 l
0m
0p
0q
0t
1y
0z
0|
0}
1#"
1&"
0'"
0*"
0+"
0,"
0-"
00"
01"
b0110 2"
03"
06"
07"
0:"
1?"
0@"
0B"
0C"
1F"
1I"
0J"
0M"
0N"
0O"
0P"
0S"
0T"
#70000000
b0111 !
1"
1#
1$
1%
b0111 &
1'
1+
16
17
1>
1B
1D
1H
b0111 I
1J
1N
1Y
1Z
1a
1e
1g
1k
b0111 l
1m
1q
1|
1}
1'"
1+"
1-"
11"
b0111 2"
13"
17"
1B"
1C"
1J"
1N"
1P"
1T"
#80000000
b1000 !
0"
0#
0$
0%
b1000 &
0'
0(
1)
1*
0+
1/
00
01
12
03
14
05
06
07
08
19
0:
1<
0=
0>
0@
1A
0B
0D
0H
b1000 I
0J
0K
1L
1M
0N
1R
0S
0T
1U
0V
1W
0X
0Y
0Z
0[
1\
0]
1_
0`
0a
0c
1d
0e
0g
0k
b1000 l
0m
0n
1o
1p
0q
1u
0v
0w
1x
0y
1z
0{
0|
0}
0!"
1""
0#"
1%"
0&"
0'"
0)"
1*"
0+"
0-"
01"
b1000 2"
03"
04"
15"
16"
07"
1;"
0<"
0="
1>"
0?"
1@"
0A"
0B"
0C"
0D"
1E"
0F"
1H"
0I"
0J"
0L"
1M"
0N"
0P"
0T"
#90000000
b1001 !
b1001 &
16
1>
1B
b1001 I
1Y
1a
1e
b1001 l
1|
1'"
1+"
b1001 2"
1B"
1J"
1N"
#100000000
b1010 !
b1010 &
0*
13
04
06
1:
1=
0>
0A
0B
b1010 I
0M
1V
0W
0Y
1]
1`
0a
0d
0e
b1010 l
0p
1y
0z
0|
1#"
1&"
0'"
0*"
0+"
b1010 2"
06"
1?"
0@"
0B"
1F"
1I"
0J"
0M"
0N"
#110000000
b1011 !
1"
1#
1$
1%
b1011 &
1'
1-
16
1>
1?
1B
1F
1H
b1011 I
1J
1P
1Y
1a
1b
1e
1i
1k
b1011 l
1m
1s
1|
1'"
1("
1+"
1/"
11"
b1011 2"
13"
19"
1B"
1J"
1K"
1N"
1R"
1T"
#120000000
b1100 !
0"
0#
0$
0%
b1100 &
0'
0)
1*
0-
11
02
03
14
06
09
0:
0<
0=
0>
0?
1@
1A
0B
0F
0H
b1100 I
0J
0L
1M
0P
1T
0U
0V
1W
0Y
0\
0]
0_
0`
0a
0b
1c
1d
0e
0i
0k
b1100 l
0m
0o
1p
0s
1w
0x
0y
1z
0|
0""
0#"
0%"
0&"
0'"
0("
1)"
1*"
0+"
0/"
01"
b1100 2"
03"
05"
16"
09"
1="
0>"
0?"
1@"
0B"
0E"
0F"
0H"
0I"
0J"
0K"
1L"
1M"
0N"
0R"
0T"
#130000000
b1101 !
1"
1#
1$
1%
b1101 &
1'
1.
16
1>
1B
1C
1G
1H
b1101 I
1J
1Q
1Y
1a
1e
1f
1j
1k
b1101 l
1m
1t
1|
1'"
1+"
1,"
10"
11"
b1101 2"
13"
1:"
1B"
1J"
1N"
1O"
1S"
1T"
#140000000
b1110 !
0"
0#
0$
0%
b1110 &
0'
0*
0.
13
04
06
1:
1=
0>
0A
0B
0C
0G
0H
b1110 I
0J
0M
0Q
1V
0W
0Y
1]
1`
0a
0d
0e
0f
0j
0k
b1110 l
0m
0p
0t
1y
0z
0|
1#"
1&"
0'"
0*"
0+"
0,"
00"
01"
b1110 2"
03"
06"
0:"
1?"
0@"
0B"
1F"
1I"
0J"
0M"
0N"
0O"
0S"
0T"
#150000000
b1111 !
b1111 &
16
1>
1B
b1111 I
1Y
1a
1e
b1111 l
1|
1'"
1+"
b1111 2"
1B"
1J"
1N"
